double_subtitle_videos/__init__.py
double_subtitle_videos/main.py
double_subtitle_videos-0.0.0.dist-info/licenses/LICENSE
double_subtitle_videos-0.0.0.dist-info/METADATA
double_subtitle_videos-0.0.0.dist-info/WHEEL
double_subtitle_videos-0.0.0.dist-info/top_level.txt
double_subtitle_videos-0.0.0.dist-info/RECORD
