Metadata-Version: 2.4
Name: double_subtitle_videos
Version: 0.0.0
Summary: Subtitle videos for language learning
Author: Alex Vig
License: The MIT License (MIT)
Project-URL: Homepage, https://github.com/jalexvig/double_subtitle_videos
Project-URL: Issues, https://github.com/jalexvig/double_subtitle_videos/issues
Classifier: Programming Language :: Python :: 3
Classifier: Operating System :: OS Independent
Requires-Python: >=3.9
License-File: LICENSE
Dynamic: license-file
